antgen/ActivityModel.py
antgen/ApplianceModel.py
antgen/LICENSE
antgen/LoadModelComponents.py
antgen/Tools.py
antgen/UserModel.py
antgen/__init__.py
antgen/antgen.py
antgen/default.conf
antgen/example1.png
antgen/example2.png
antgen/main.py
antgen/mapping.conf
antgen/requirements.txt
antgen/activities/HOUSEHOLD/dry_clothes.conf
antgen/activities/HOUSEHOLD/ironing.conf
antgen/activities/HOUSEHOLD/vacuum.conf
antgen/activities/HOUSEHOLD/wash_laundry.conf
antgen/activities/KITCHEN/dishwasher.conf
antgen/activities/KITCHEN/fried_egg.conf
antgen/activities/KITCHEN/heating_lunch.conf
antgen/activities/KITCHEN/preparing_breakfast.conf
antgen/activities/KITCHEN/preparing_dinner.conf
antgen/activities/KITCHEN/refrigerator.conf
antgen/activities/LEISURE/listen_music.conf
antgen/activities/LEISURE/use_pc.conf
antgen/activities/LEISURE/watch_tv.conf
antgen/appliances/AMPLIFIER/dev_AF6490/mode0
antgen/appliances/BREADCUTTER/dev_B7DF9D/mode0
antgen/appliances/BREADCUTTER/dev_B7DF9D/mode1
antgen/appliances/CDPLAYER/dev_C3E6D1/mode0
antgen/appliances/COFFEEMAKER/ECO-H1/mode0
antgen/appliances/COFFEEMAKER/ECO-H1/mode1
antgen/appliances/COFFEEMAKER/dev_735E9D/mode0
antgen/appliances/COFFEEMAKER/dev_735E9D/mode1
antgen/appliances/COOKINGSTOVE/dev_D33097/mode0
antgen/appliances/COOKINGSTOVE/dev_D33097/mode1
antgen/appliances/COOKINGSTOVE/dev_D33097/mode2
antgen/appliances/COOKINGSTOVE/dev_D33097/mode3
antgen/appliances/DISHWASHER/dev_995BAC/mode0
antgen/appliances/DRYER/ECO-H1/mode0
antgen/appliances/DRYER/ECO-H1/mode1
antgen/appliances/DRYER/ECO-H1/mode2
antgen/appliances/FREEZER/ECO-H1/mode0
antgen/appliances/FREEZER/ECO-H1/mode1
antgen/appliances/FREEZER/ECO-H1/mode2
antgen/appliances/FREEZER/ECO-H1/mode3
antgen/appliances/FREEZER/ECO-H1/mode4
antgen/appliances/FREEZER/ECO-H1/mode5
antgen/appliances/FREEZER/ECO-H1/mode6
antgen/appliances/FREEZER/ECO-H1/mode7
antgen/appliances/FREEZER/ECO-H1/mode8
antgen/appliances/FREEZER/ECO-H1/mode9
antgen/appliances/IRON/dev_D337C2/mode0
antgen-0.4.1.dist-info/LICENSE
antgen-0.4.1.dist-info/METADATA
antgen-0.4.1.dist-info/WHEEL
antgen-0.4.1.dist-info/top_level.txt
antgen-0.4.1.dist-info/RECORD
