Metadata-Version: 2.1
Name: antgen
Version: 0.4.1
Summary: This tool generates synthetic macroscopic load signatures for their use in conjunction with NILM (load disaggregation) tools.
Author: Nuno Velosa
Author-email: Nuno Velosa <nunovelosa@hotmail.com>
Project-URL: Homepage, https://gitlab.com/nunovelosa/antgen
Project-URL: Bug Tracker, https://gitlab.com/nunovelosa/antgen/issues
Classifier: Programming Language :: Python :: 3
Classifier: License :: OSI Approved :: MIT License
Classifier: Operating System :: OS Independent
Requires-Python: >=3.7
License-File: LICENSE
